MANIFEST.in
README.md
setup.py
AWSpot.egg-info/PKG-INFO
AWSpot.egg-info/SOURCES.txt
AWSpot.egg-info/dependency_links.txt
AWSpot.egg-info/requires.txt
AWSpot.egg-info/top_level.txt
awspot/__init__.py
awspot/actions/__init__.py
awspot/actions/base.py
awspot/actions/ec2/__init__.py
awspot/actions/ec2/base.py
awspot/actions/ec2/launch.py
awspot/actions/ec2/list_active.py
awspot/actions/ec2/ssh.py
awspot/actions/ec2/terminate.py
awspot/etc/__init__.py
awspot/etc/base_argparser.py
awspot/managers/__init__.py
awspot/managers/base.py
awspot/managers/ec2Manager.py
awspot/test/__init__.py
awspot/test/ec2_test.py
bin/awspot