Metadata-Version: 1.2
Name: AWSpot
Version: 0.0.5
Summary: Utility for managing AWS spot resources.
Home-page: http://pypi.python.org/pypi/AWSpot/
Author: Rob Dalton
Author-email: rob@robdalton.me
License: LICENSE
Platform: UNKNOWN
Classifier: Programming Language :: Python :: 3.6
Requires-Python: >=3.6
